### 字节码分析

``` java
// Hello.java
package homework;
public class Hello {

    public static void main(String[] args) {
        Hello hello = new Hello();
        int[] intArr = {5,4,3,2,1};
        int sum = 0;
        for (int i : intArr) {
            sum = hello.add(sum, i);
            if(sum >= 10){
                break;
            }
        }
        for (int i = 0; i < intArr.length; i++) {
            sum = hello.sub(sum, i);
        }
        double ret = 1;
        for (int i : intArr) {
            ret = hello.mul((int) ret, i);
        }
        for (int i = 0; i < intArr.length; i++) {
            ret = hello.div(ret, i);
        }
    }

    public int add(int a, int b){
        return a + b;
    }

    private int sub(int a, int b){
        return a - b;
    }

    private int mul(int a, int b){
        return a * b;
    }

    private double div(double a, double b){
        return a / b;
    }
}
```


``` java
// Hello.class 字节码
Classfile /D:/work/JAVA-01/Week_01/code/homework/Hello.class
  Last modified 2021-1-10; size 1265 bytes
  MD5 checksum 9175c9a128739f8c575b395c22ca4bfe
  Compiled from "Hello.java"
public class homework.Hello
  minor version: 0
  major version: 52
// 52表示java版本为 java8
  flags: ACC_PUBLIC, ACC_SUPER
Constant pool:
// 常量池
   #1 = Methodref          #8.#42         // java/lang/Object."<init>":()V
   #2 = Class              #43            // homework/Hello
   #3 = Methodref          #2.#42         // homework/Hello."<init>":()V
   #4 = Methodref          #2.#44         // homework/Hello.add:(II)I
   #5 = Methodref          #2.#45         // homework/Hello.sub:(II)I
   #6 = Methodref          #2.#46         // homework/Hello.mul:(II)I
   #7 = Methodref          #2.#47         // homework/Hello.div:(DD)D
// object类的init() Hello的init() Hello的加减乘除方法 
// 常量池中Methodref只有非静态方法 没有静态方法（main就没有）
   #8 = Class              #48            // java/lang/Object
   #9 = Utf8               <init>
  #10 = Utf8               ()V
  #11 = Utf8               Code
  #12 = Utf8               LineNumberTable
  #13 = Utf8               LocalVariableTable
  #14 = Utf8               this
  #15 = Utf8               Lhomework/Hello;
  #16 = Utf8               main
  #17 = Utf8               ([Ljava/lang/String;)V
  #18 = Utf8               i
  #19 = Utf8               I
  #20 = Utf8               args
  #21 = Utf8               [Ljava/lang/String;
  #22 = Utf8               hello
  #23 = Utf8               intArr
  #24 = Utf8               [I
  #25 = Utf8               sum
  #26 = Utf8               ret
  #27 = Utf8               D
  #28 = Utf8               StackMapTable
  #29 = Class              #21            // "[Ljava/lang/String;"
  #30 = Class              #43            // homework/Hello
  #31 = Class              #24            // "[I"
  #32 = Utf8               add
  #33 = Utf8               (II)I
  #34 = Utf8               a
  #35 = Utf8               b
  #36 = Utf8               sub
  #37 = Utf8               mul
  #38 = Utf8               div
  #39 = Utf8               (DD)D
  #40 = Utf8               SourceFile
  #41 = Utf8               Hello.java
  #42 = NameAndType        #9:#10         // "<init>":()V
  #43 = Utf8               homework/Hello
  #44 = NameAndType        #32:#33        // add:(II)I
  #45 = NameAndType        #36:#33        // sub:(II)I
  #46 = NameAndType        #37:#33        // mul:(II)I
  #47 = NameAndType        #38:#39        // div:(DD)D
  #48 = Utf8               java/lang/Object
{
  public homework.Hello();
// Hello的默认构造方法
    descriptor: ()V
// 无参数 返回值为void
    flags: ACC_PUBLIC
// 访问限定是public
    Code:
      stack=1, locals=1, args_size=1
// 有一个局部变量 locals = 1 是 this
         0: aload_0
         1: invokespecial #1                  // Method java/lang/Object."<init>":()V
         4: return
      LineNumberTable:
        line 2: 0
      LocalVariableTable:
        Start  Length  Slot  Name   Signature
            0       5     0  this   Lhomework/Hello;

  public static void main(java.lang.String[]);
// main方法
    descriptor: ([Ljava/lang/String;)V
// 参数为 字符串对象数组 返回值void
    flags: ACC_PUBLIC, ACC_STATIC
// public static
    Code:
      stack=5, locals=10, args_size=1
// 10个局部变量 args[] hello intArr sum intArr.length ret i*4 
         0: new           #2                  // class homework/Hello
         3: dup
         4: invokespecial #3                  // Method "<init>":()V
         7: astore_1
// 压栈存储 slot=1的hello对象
         8: iconst_5
// 给 int型变量赋值 5 （定义数组长度为5）
         9: newarray       int
        11: dup
        12: iconst_0
        13: iconst_5
        14: iastore
        15: dup
        16: iconst_1
        17: iconst_4
        18: iastore
        19: dup
        20: iconst_2
        21: iconst_3
        22: iastore
        23: dup
        24: iconst_3
        25: iconst_2
        26: iastore
        27: dup
        28: iconst_4
        29: iconst_1
        30: iastore
        31: astore_2
        32: iconst_0
// 定义并构建数组完成 将数组存储到slot=2的变量中
// for循环的初始化和判断操作
        33: istore_3
        34: aload_2
        35: astore        4
        37: aload         4
        39: arraylength
        40: istore        5
        42: iconst_0
        43: istore        6
// for循环中的判断 i < arraylength
        45: iload         6
        47: iload         5
        49: if_icmpge     82
        52: aload         4
        54: iload         6
        56: iaload
        57: istore        7
// 调用add方法开始
        59: aload_1
        60: iload_3
        61: iload         7
        63: invokespecial #4                  // Method add:(II)I
        66: istore_3
        67: iload_3
        68: bipush        10
// 大于10的时候
        70: if_icmplt     76
// break
        73: goto          82
// for循环中的i++
        76: iinc          6, 1
        79: goto          45
        82: iconst_0
        83: istore        4
        85: iload         4
        87: aload_2
        88: arraylength
        89: if_icmpge     106
// 调用sub方法
        92: aload_1
        93: iload_3
        94: iload         4
        96: invokespecial #5                  // Method sub:(II)I
        99: istore_3
       100: iinc          4, 1
       103: goto          85
       106: dconst_1
       107: dstore        4
       109: aload_2
       110: astore        6
       112: aload         6
       114: arraylength
       115: istore        7
       117: iconst_0
       118: istore        8
       120: iload         8
       122: iload         7
       124: if_icmpge     152
       127: aload         6
       129: iload         8
       131: iaload
       132: istore        9
// 调用mul方法
       134: aload_1
       135: dload         4
       137: d2i
       138: iload         9
       140: invokespecial #6                  // Method mul:(II)I
       143: i2d
       144: dstore        4
       146: iinc          8, 1
       149: goto          120
       152: iconst_0
       153: istore        6
       155: iload         6
       157: aload_2
       158: arraylength
       159: if_icmpge     179
// 调用div方法
       162: aload_1
       163: dload         4
       165: iload         6
       167: i2d
       168: invokespecial #7                  // Method div:(DD)D
       171: dstore        4
       173: iinc          6, 1
       176: goto          155
       179: return
      LineNumberTable:
// 指令0 对应的源代码中的第5行
        line 5: 0
// 指令8开始 对应源代码中第6行
        line 6: 8
        line 7: 32
        line 8: 34
        line 9: 59
        line 10: 67
        line 11: 73
        line 8: 76
        line 14: 82
        line 15: 92
        line 14: 100
        line 17: 106
        line 18: 109
        line 19: 134
        line 18: 146
        line 21: 152
        line 22: 162
        line 21: 173
        line 24: 179
      LocalVariableTable:
        Start  Length  Slot  Name   Signature
           59      17     7     i   I
           85      21     4     i   I
          134      12     9     i   I
          155      24     6     i   I
            0     180     0  args   [Ljava/lang/String;
            8     172     1 hello   Lhomework/Hello;
           32     148     2 intArr   [I
           34     146     3   sum   I
          109      71     4   ret   D
      StackMapTable: number_of_entries = 9
        frame_type = 255 /* full_frame */
          offset_delta = 45
          locals = [ class "[Ljava/lang/String;", class homework/Hello, class "[I", int, class "[I", int, int ]
          stack = []
        frame_type = 30 /* same */
        frame_type = 248 /* chop */
          offset_delta = 5
        frame_type = 252 /* append */
          offset_delta = 2
          locals = [ int ]
        frame_type = 250 /* chop */
          offset_delta = 20
        frame_type = 255 /* full_frame */
          offset_delta = 13
          locals = [ class "[Ljava/lang/String;", class homework/Hello, class "[I", int, double, class "[I", int, int ]
          stack = []
        frame_type = 248 /* chop */
          offset_delta = 31
        frame_type = 252 /* append */
          offset_delta = 2
          locals = [ int ]
        frame_type = 250 /* chop */
          offset_delta = 23

// 只有public的方法会被详细列出来
     public int add(int, int);
        descriptor: (II)I
        flags: ACC_PUBLIC
        Code:
          stack=2, locals=3, args_size=3
             0: iload_1
             1: iload_2
             2: iadd
             3: ireturn
          LineNumberTable:
            line 27: 0
          LocalVariableTable:
            Start  Length  Slot  Name   Signature
                0       4     0  this   Lhomework/Hello;
                0       4     1     a   I
                0       4     2     b   I

}
SourceFile: "Hello.java"
```
